jusflpyroot/__init__.py
jusflpyroot/numth1.py
jusflpyroot-0.1.9.dist-info/METADATA
jusflpyroot-0.1.9.dist-info/WHEEL
jusflpyroot-0.1.9.dist-info/RECORD
