Metadata-Version: 2.4
Name: jusflpyroot
Version: 0.1.9
Summary: Useful tools for root in python
Requires-Python: >=3.12
Requires-Dist: click>=8.2.1
Requires-Dist: console>=0.9911
Requires-Dist: iminuit>=2.31.1
Requires-Dist: matplotlib>=3.10.3
Requires-Dist: numpy<2.2.0
Requires-Dist: pyqt5>=5.15.11
Requires-Dist: scipy>=1.16.0
